src/js/chef/dist/apple-touch-icon-180x180.png
src/js/chef/dist/assets/flUhRq6tzZclQEJ-Vdg-IuiaDsNa-fd84f88b.woff
src/js/chef/dist/assets/flUhRq6tzZclQEJ-Vdg-IuiaDsNcIhQ8tQ-4a4dbc62.woff2
src/js/chef/dist/assets/index-58daebd1.css
src/js/chef/dist/assets/index-95ae1ffa.js
src/js/chef/dist/assets/logo-efaedf55.svg
src/js/chef/dist/assets/notfound-f5f483aa.jpg
src/js/chef/dist/favicon.ico
src/js/chef/dist/favicon_old.ico
src/js/chef/dist/index.html
src/js/chef/dist/logo.svg
src/js/chef/dist/manifest.webmanifest
src/js/chef/dist/maskable-icon-512x512.png
src/js/chef/dist/pwa-192x192.png
src/js/chef/dist/pwa-512x512.png
src/js/chef/dist/pwa-64x64.png
src/js/chef/dist/registerSW.js
src/js/chef/dist/sw.js
src/js/chef/dist/workbox-3e911b1d.js
chef/__init__.py
chef/api/__init__.py
chef/api/categories.py
chef/api/common.py
chef/api/images.py
chef/api/ingredients.py
chef/api/recipes.py
chef/api/tags.py
chef/api/units.py
chef/controllers.py
chef/frontend.py
chef/image/__init__.py
chef/image/storage.py
chef/image/thumbnailer.py
chef/images.py
chef/main.py
chef/models.py
chef/schemas.py
chef/scripts/__init__.py
chef/scripts/migrate_images.py
chef/session.py
chef/settings.py
migrations/README
migrations/__init__.py
migrations/alembic.ini
migrations/env.py
migrations/migrate.py
migrations/script.py.mako
migrations/versions/3251a114750c_.py
migrations/versions/39659baca9b3_.py
migrations/versions/998321576878_.py
migrations/versions/__init__.py
migrations/versions/aaa1b50ab63e_add_images.py
migrations/versions/b8b797b55d1b_.py
migrations/versions/c7b802139fbf_tweak_ingredient_item.py
migrations/versions/e454e6860914_timestamps.py
migrations/versions/ea9e0ff5a7ff_add_ingredient_item_order.py
migrations/versions/f91610b78d55_.py
chef_recipes-2.5.5.dist-info/METADATA
chef_recipes-2.5.5.dist-info/WHEEL
chef_recipes-2.5.5.dist-info/entry_points.txt
chef_recipes-2.5.5.dist-info/RECORD
