Metadata-Version: 2.3
Name: chef-recipes
Version: 2.5.5
Summary: Personal recipe management app.
License: MIT
Keywords: food,recipes,culinary
Author: Your Name
Author-email: you@example.com
Requires-Python: >=3.8,<4.0
Classifier: Framework :: FastAPI
Classifier: License :: OSI Approved :: MIT License
Classifier: Programming Language :: Python :: 3
Classifier: Programming Language :: Python :: 3.8
Classifier: Programming Language :: Python :: 3.9
Classifier: Programming Language :: Python :: 3.10
Classifier: Programming Language :: Python :: 3.11
Classifier: Programming Language :: Python :: 3.12
Classifier: Programming Language :: Python :: 3.13
Requires-Dist: alembic (>=1.11.1,<2.0.0)
Requires-Dist: fastapi (==0.*)
Requires-Dist: httpx (>=0.27.0,<0.28.0)
Requires-Dist: loguru (>=0.7.0,<0.8.0)
Requires-Dist: pillow (>=10.2.0,<11.0.0)
Requires-Dist: pillow-avif-plugin (>=1.4.2,<2.0.0)
Requires-Dist: pydantic-settings (>=2.1.0,<3.0.0)
Requires-Dist: python-multipart
Requires-Dist: sentry-sdk[fastapi] (>=2.12.0,<3.0.0)
Requires-Dist: sqlalchemy (>=2.0.16,<3.0.0)
Requires-Dist: typer[all]
Requires-Dist: uvicorn (>=0.22.0,<0.23.0)
Project-URL: Repository, https://github.com/xyzjonas/chef
